[
  {
    "ip": "Enchantix",
    "created": "2020-05-21 17:09:01 -0500",
    "source": "§8[§c§lM§8] §9F_x§r",
    "expires": "forever",
    "reason": "The Ban Hammer has spoken!"
  },
  {
    "ip": "angelomazza1993",
    "created": "2020-05-21 17:09:06 -0500",
    "source": "§8[§c§lM§8] §9F_x§r",
    "expires": "forever",
    "reason": "The Ban Hammer has spoken!"
  },
  {
    "ip": "94.134.92.176",
    "created": "2020-05-28 16:31:08 -0500",
    "source": "AikoPlayz",
    "expires": "forever",
    "reason": "Banned by an operator."
  }
]